<metadata xml:lang="pl"><Esri><CreaDate>20220406</CreaDate><CreaTime>10223400</CreaTime><ArcGISFormat>1.0</ArcGISFormat><SyncOnce>FALSE</SyncOnce><DataProperties><lineage><Process ToolSource="c:\program files\arcgis\pro\Resources\ArcToolbox\toolboxes\Geostatistical Analyst Tools.tbx\GALayerToPoints" Date="20220406" Time="102234">GALayerToPoints "KD\Kriging D" Punktpomiarowy_training15 TEMP "C:\Users\monik\OneDrive - University of Warmia and Mazuria in Olsztyn\Pulpit\semestr 3\Geostatystyka (Ogryzek, Ciski)\ćwiczenia\sprawozdanie 1\Sprawozdanie 1 -projekt\Sprawozdanie 1 -projekt.gdb\GALayerToPointsKD15" ALL ELEVATION Meter</Process><Process ToolSource="c:\program files\arcgis\pro\Resources\ArcToolbox\toolboxes\Conversion Tools.tbx\TableToTable" Date="20220406" Time="102306">TableToTable KD\GALayerToPointsKD15 "C:\Users\monik\OneDrive - University of Warmia and Mazuria in Olsztyn\Pulpit\semestr 3\Geostatystyka (Ogryzek, Ciski)\ćwiczenia\sprawozdanie 1\Sprawozdanie 1 -projekt\spr2-tabele,wyniki 85_15" KD_85_15.csv # "ICAO "ICAO" true true false 4 Text 0 0,First,#,KD\GALayerToPointsKD15,ICAO,0,4;OBS_DATETI "OBS_DATETI" true true false 8 Date 0 0,First,#,KD\GALayerToPointsKD15,OBS_DATETI,-1,-1;STATION_NA "STATION_NA" true true false 125 Text 0 0,First,#,KD\GALayerToPointsKD15,STATION_NA,0,125;COUNTRY "COUNTRY" true true false 50 Text 0 0,First,#,KD\GALayerToPointsKD15,COUNTRY,0,50;ELEVATION "ELEVATION" true true false 4 Float 0 0,First,#,KD\GALayerToPointsKD15,ELEVATION,-1,-1;TEMP "TEMP" true true false 4 Float 0 0,First,#,KD\GALayerToPointsKD15,TEMP,-1,-1;DEW_POINT "DEW_POINT" true true false 4 Float 0 0,First,#,KD\GALayerToPointsKD15,DEW_POINT,-1,-1;R_HUMIDITY "R_HUMIDITY" true true false 4 Long 0 0,First,#,KD\GALayerToPointsKD15,R_HUMIDITY,-1,-1;WIND_DIREC "WIND_DIREC" true true false 4 Long 0 0,First,#,KD\GALayerToPointsKD15,WIND_DIREC,-1,-1;WIND_SPEED "WIND_SPEED" true true false 4 Long 0 0,First,#,KD\GALayerToPointsKD15,WIND_SPEED,-1,-1;WIND_GUST "WIND_GUST" true true false 4 Long 0 0,First,#,KD\GALayerToPointsKD15,WIND_GUST,-1,-1;WIND_CHILL "WIND_CHILL" true true false 4 Float 0 0,First,#,KD\GALayerToPointsKD15,WIND_CHILL,-1,-1;VISIBILITY "VISIBILITY" true true false 4 Long 0 0,First,#,KD\GALayerToPointsKD15,VISIBILITY,-1,-1;PRESSURE "PRESSURE" true true false 4 Float 0 0,First,#,KD\GALayerToPointsKD15,PRESSURE,-1,-1;SKY_CONDTN "SKY_CONDTN" true true false 254 Text 0 0,First,#,KD\GALayerToPointsKD15,SKY_CONDTN,0,254;WEATHER "WEATHER" true true false 254 Text 0 0,First,#,KD\GALayerToPointsKD15,WEATHER,0,254;REMARKS "REMARKS" true true false 254 Text 0 0,First,#,KD\GALayerToPointsKD15,REMARKS,0,254;HEAT_INDEX "HEAT_INDEX" true true false 4 Float 0 0,First,#,KD\GALayerToPointsKD15,HEAT_INDEX,-1,-1;LATITUDE "LATITUDE" true true false 4 Float 0 0,First,#,KD\GALayerToPointsKD15,LATITUDE,-1,-1;LONGITUDE "LONGITUDE" true true false 4 Float 0 0,First,#,KD\GALayerToPointsKD15,LONGITUDE,-1,-1;Included "Included" true true false 255 Text 0 0,First,#,KD\GALayerToPointsKD15,Included,0,255;Predicted "Predicted" true true false 8 Double 0 0,First,#,KD\GALayerToPointsKD15,Predicted,-1,-1;Error "Error" true true false 8 Double 0 0,First,#,KD\GALayerToPointsKD15,Error,-1,-1;StdError "Standard Error" true true false 8 Double 0 0,First,#,KD\GALayerToPointsKD15,StdError,-1,-1;Stdd_Error "Standardized Error" true true false 8 Double 0 0,First,#,KD\GALayerToPointsKD15,Stdd_Error,-1,-1;NormValue "Normal Value" true true false 8 Double 0 0,First,#,KD\GALayerToPointsKD15,NormValue,-1,-1" #</Process></lineage><itemProps><itemName Sync="TRUE">KD_85_15.csv</itemName><imsContentType Sync="TRUE">005</imsContentType><itemLocation><linkage Sync="TRUE">file://\\DESKTOP-AHOFTH9\C$\Users\monik\OneDrive - University of Warmia and Mazuria in Olsztyn\Pulpit\semestr 3\Geostatystyka (Ogryzek, Ciski)\ćwiczenia\sprawozdanie 1\Sprawozdanie 1 -projekt\spr2-tabele,wyniki 85_15\KD_85_15.csv</linkage><protocol Sync="TRUE">Local Area Network</protocol></itemLocation><itemSize Sync="TRUE">0.000</itemSize></itemProps></DataProperties><SyncDate>20220406</SyncDate><SyncTime>10230600</SyncTime><ModDate>20220406</ModDate><ModTime>10230600</ModTime></Esri><ga><model name="Kriging"><dataset Label="Dataset" ParamName="dataset1" dataset-type="DVA"/><dataset Label="Dataset 2" ParamName="dataset2" dataset-type="DVA" optional="true"/><dataset Label="Dataset 3" ParamName="dataset3" dataset-type="DVA" optional="true"/><dataset Label="Dataset 4" ParamName="dataset4" dataset-type="DVA" optional="true"/><dataset Label="Decluster's Clipping Dataset" ParamName="declusterPolygons1" dataset-type="Generic" sub-type="polygon" optional="true" visible="false"/><dataset Label="Decluster's Clipping Dataset 2" ParamName="declusterPolygons2" dataset-type="Generic" sub-type="polygon" optional="true" visible="false"/><dataset Label="Decluster's Clipping Dataset 3" ParamName="declusterPolygons3" dataset-type="Generic" sub-type="polygon" optional="true" visible="false"/><dataset Label="Decluster's Clipping Dataset 4" ParamName="declusterPolygons4" dataset-type="Generic" sub-type="polygon" optional="true" visible="false"/><enum name="KrigingMethodType">Disjunctive</enum><enum name="KrigingResultType">Prediction</enum><items name="Datasets"><item name="Dataset"><enum name="TrendType">None</enum><model name="TransformationNormalScore"><enum name="ApproximationMethodType">DensitySkew</enum><value name="Kernels" auto="false">8</value><enum name="BaseDistribution" auto="false">BaseStudentTDistribution</enum></model>
					<model name="NeighbourSearch" options="CopyFromVariogram"><enum name="Type">Standard</enum><value name="NeighboursMax" auto="false">5</value><value name="NeighboursMin" auto="false">2</value><enum name="SectorType">Four45</enum><value name="MajorSemiaxis" auto="false">1772065.8420975776</value><value name="MinorSemiaxis" auto="false">1772065.8420975776</value><value name="Angle">0</value></model>
				</item></items><model name="Variogram"><value name="DatalayerCount">1</value><value name="NumberOfLags" auto="false">12</value><value name="LagSize" auto="false">275842.4629973422</value><enum name="PairsType" auto="false">Covariance</enum><bool name="NuggetOn">true</bool><value name="Nugget" auto="false">0.4163950776899107</value><bool name="VariogramModelAuto">false</bool><model name="VariogramModel"><enum name="ModelType">Stable</enum><value name="Parameter" auto="false">2</value><value name="Range" auto="false">1772065.8420975776</value><bool name="Anisotropy">false</bool><value name="Sill" auto="false">0.5831603161835247</value></model>
			</model>
		</model>
	</ga><dataIdInfo><envirDesc Sync="TRUE">Microsoft Windows 10 Version 10.0 (Build 19044) ; Esri ArcGIS 12.8.3.29751</envirDesc><dataLang><languageCode value="pol" Sync="TRUE"></languageCode><countryCode value="POL" Sync="TRUE"></countryCode></dataLang><idCitation><resTitle Sync="TRUE">KD_85_15.csv</resTitle><presForm><PresFormCd value="001" Sync="TRUE"></PresFormCd></presForm></idCitation></dataIdInfo><mdLang><languageCode value="pol" Sync="TRUE"></languageCode><countryCode value="POL" Sync="TRUE"></countryCode></mdLang><distInfo><distFormat><formatName Sync="TRUE">Text File</formatName></distFormat><distTranOps><transSize Sync="TRUE">0.000</transSize></distTranOps></distInfo><mdHrLv><ScopeCd value="007" Sync="TRUE"></ScopeCd></mdHrLv><mdHrLvName Sync="TRUE">non-geographic dataset</mdHrLvName><eainfo><detailed Name="KD_85_15.csv"><enttyp><enttypl Sync="TRUE">KD_85_15.csv</enttypl><enttypt Sync="TRUE">Table</enttypt><enttypc Sync="TRUE">0</enttypc></enttyp><attr><attrlabl Sync="TRUE">OID_</attrlabl><attalias Sync="TRUE">OID_</attalias><attrtype Sync="TRUE">Integer</attrtype><attwidth Sync="TRUE">4</attwidth><atprecis Sync="TRUE">0</atprecis><attscale Sync="TRUE">0</attscale></attr><attr><attrlabl Sync="TRUE">ICAO</attrlabl><attalias Sync="TRUE">ICAO</attalias><attrtype Sync="TRUE">String</attrtype><attwidth Sync="TRUE">4</attwidth><atprecis Sync="TRUE">0</atprecis><attscale Sync="TRUE">0</attscale></attr><attr><attrlabl Sync="TRUE">OBS_DATETI</attrlabl><attalias Sync="TRUE">OBS_DATETI</attalias><attrtype Sync="TRUE">Date</attrtype><attwidth Sync="TRUE">8</attwidth><atprecis Sync="TRUE">0</atprecis><attscale Sync="TRUE">0</attscale></attr><attr><attrlabl Sync="TRUE">STATION_NA</attrlabl><attalias Sync="TRUE">STATION_NA</attalias><attrtype Sync="TRUE">String</attrtype><attwidth Sync="TRUE">125</attwidth><atprecis Sync="TRUE">0</atprecis><attscale Sync="TRUE">0</attscale></attr><attr><attrlabl Sync="TRUE">COUNTRY</attrlabl><attalias Sync="TRUE">COUNTRY</attalias><attrtype Sync="TRUE">String</attrtype><attwidth Sync="TRUE">50</attwidth><atprecis Sync="TRUE">0</atprecis><attscale Sync="TRUE">0</attscale></attr><attr><attrlabl Sync="TRUE">ELEVATION</attrlabl><attalias Sync="TRUE">ELEVATION</attalias><attrtype Sync="TRUE">Single</attrtype><attwidth Sync="TRUE">4</attwidth><atprecis Sync="TRUE">0</atprecis><attscale Sync="TRUE">0</attscale></attr><attr><attrlabl Sync="TRUE">TEMP</attrlabl><attalias Sync="TRUE">TEMP</attalias><attrtype Sync="TRUE">Single</attrtype><attwidth Sync="TRUE">4</attwidth><atprecis Sync="TRUE">0</atprecis><attscale Sync="TRUE">0</attscale></attr><attr><attrlabl Sync="TRUE">DEW_POINT</attrlabl><attalias Sync="TRUE">DEW_POINT</attalias><attrtype Sync="TRUE">Single</attrtype><attwidth Sync="TRUE">4</attwidth><atprecis Sync="TRUE">0</atprecis><attscale Sync="TRUE">0</attscale></attr><attr><attrlabl Sync="TRUE">R_HUMIDITY</attrlabl><attalias Sync="TRUE">R_HUMIDITY</attalias><attrtype Sync="TRUE">Integer</attrtype><attwidth Sync="TRUE">4</attwidth><atprecis Sync="TRUE">0</atprecis><attscale Sync="TRUE">0</attscale></attr><attr><attrlabl Sync="TRUE">WIND_DIREC</attrlabl><attalias Sync="TRUE">WIND_DIREC</attalias><attrtype Sync="TRUE">Integer</attrtype><attwidth Sync="TRUE">4</attwidth><atprecis Sync="TRUE">0</atprecis><attscale Sync="TRUE">0</attscale></attr><attr><attrlabl Sync="TRUE">WIND_SPEED</attrlabl><attalias Sync="TRUE">WIND_SPEED</attalias><attrtype Sync="TRUE">Integer</attrtype><attwidth Sync="TRUE">4</attwidth><atprecis Sync="TRUE">0</atprecis><attscale Sync="TRUE">0</attscale></attr><attr><attrlabl Sync="TRUE">WIND_GUST</attrlabl><attalias Sync="TRUE">WIND_GUST</attalias><attrtype Sync="TRUE">Integer</attrtype><attwidth Sync="TRUE">4</attwidth><atprecis Sync="TRUE">0</atprecis><attscale Sync="TRUE">0</attscale></attr><attr><attrlabl Sync="TRUE">WIND_CHILL</attrlabl><attalias Sync="TRUE">WIND_CHILL</attalias><attrtype Sync="TRUE">Single</attrtype><attwidth Sync="TRUE">4</attwidth><atprecis Sync="TRUE">0</atprecis><attscale Sync="TRUE">0</attscale></attr><attr><attrlabl Sync="TRUE">VISIBILITY</attrlabl><attalias Sync="TRUE">VISIBILITY</attalias><attrtype Sync="TRUE">Integer</attrtype><attwidth Sync="TRUE">4</attwidth><atprecis Sync="TRUE">0</atprecis><attscale Sync="TRUE">0</attscale></attr><attr><attrlabl Sync="TRUE">PRESSURE</attrlabl><attalias Sync="TRUE">PRESSURE</attalias><attrtype Sync="TRUE">Single</attrtype><attwidth Sync="TRUE">4</attwidth><atprecis Sync="TRUE">0</atprecis><attscale Sync="TRUE">0</attscale></attr><attr><attrlabl Sync="TRUE">SKY_CONDTN</attrlabl><attalias Sync="TRUE">SKY_CONDTN</attalias><attrtype Sync="TRUE">String</attrtype><attwidth Sync="TRUE">254</attwidth><atprecis Sync="TRUE">0</atprecis><attscale Sync="TRUE">0</attscale></attr><attr><attrlabl Sync="TRUE">WEATHER</attrlabl><attalias Sync="TRUE">WEATHER</attalias><attrtype Sync="TRUE">String</attrtype><attwidth Sync="TRUE">254</attwidth><atprecis Sync="TRUE">0</atprecis><attscale Sync="TRUE">0</attscale></attr><attr><attrlabl Sync="TRUE">REMARKS</attrlabl><attalias Sync="TRUE">REMARKS</attalias><attrtype Sync="TRUE">String</attrtype><attwidth Sync="TRUE">254</attwidth><atprecis Sync="TRUE">0</atprecis><attscale Sync="TRUE">0</attscale></attr><attr><attrlabl Sync="TRUE">HEAT_INDEX</attrlabl><attalias Sync="TRUE">HEAT_INDEX</attalias><attrtype Sync="TRUE">Single</attrtype><attwidth Sync="TRUE">4</attwidth><atprecis Sync="TRUE">0</atprecis><attscale Sync="TRUE">0</attscale></attr><attr><attrlabl Sync="TRUE">LATITUDE</attrlabl><attalias Sync="TRUE">LATITUDE</attalias><attrtype Sync="TRUE">Single</attrtype><attwidth Sync="TRUE">4</attwidth><atprecis Sync="TRUE">0</atprecis><attscale Sync="TRUE">0</attscale></attr><attr><attrlabl Sync="TRUE">LONGITUDE</attrlabl><attalias Sync="TRUE">LONGITUDE</attalias><attrtype Sync="TRUE">Single</attrtype><attwidth Sync="TRUE">4</attwidth><atprecis Sync="TRUE">0</atprecis><attscale Sync="TRUE">0</attscale></attr><attr><attrlabl Sync="TRUE">Included</attrlabl><attalias Sync="TRUE">Included</attalias><attrtype Sync="TRUE">String</attrtype><attwidth Sync="TRUE">255</attwidth><atprecis Sync="TRUE">0</atprecis><attscale Sync="TRUE">0</attscale></attr><attr><attrlabl Sync="TRUE">Predicted</attrlabl><attalias Sync="TRUE">Predicted</attalias><attrtype Sync="TRUE">Double</attrtype><attwidth Sync="TRUE">8</attwidth><atprecis Sync="TRUE">0</atprecis><attscale Sync="TRUE">0</attscale></attr><attr><attrlabl Sync="TRUE">Error</attrlabl><attalias Sync="TRUE">Error</attalias><attrtype Sync="TRUE">Double</attrtype><attwidth Sync="TRUE">8</attwidth><atprecis Sync="TRUE">0</atprecis><attscale Sync="TRUE">0</attscale></attr><attr><attrlabl Sync="TRUE">StdError</attrlabl><attalias Sync="TRUE">StdError</attalias><attrtype Sync="TRUE">Double</attrtype><attwidth Sync="TRUE">8</attwidth><atprecis Sync="TRUE">0</atprecis><attscale Sync="TRUE">0</attscale></attr><attr><attrlabl Sync="TRUE">Stdd_Error</attrlabl><attalias Sync="TRUE">Stdd_Error</attalias><attrtype Sync="TRUE">Double</attrtype><attwidth Sync="TRUE">8</attwidth><atprecis Sync="TRUE">0</atprecis><attscale Sync="TRUE">0</attscale></attr><attr><attrlabl Sync="TRUE">NormValue</attrlabl><attalias Sync="TRUE">NormValue</attalias><attrtype Sync="TRUE">Double</attrtype><attwidth Sync="TRUE">8</attwidth><atprecis Sync="TRUE">0</atprecis><attscale Sync="TRUE">0</attscale></attr></detailed></eainfo><mdDateSt Sync="TRUE">20220406</mdDateSt></metadata>
